nest_asyncio.py
nest_asyncio-1.5.9.dist-info/LICENSE
nest_asyncio-1.5.9.dist-info/METADATA
nest_asyncio-1.5.9.dist-info/WHEEL
nest_asyncio-1.5.9.dist-info/top_level.txt
nest_asyncio-1.5.9.dist-info/RECORD
