Metadata-Version: 2.1
Name: nest_asyncio
Version: 1.5.9
Summary: Patch asyncio to allow nested event loops
Home-page: https://github.com/erdewit/nest_asyncio
Author: Ewald R. de Wit
Author-email: ewald.de.wit@gmail.com
License: BSD
Keywords: asyncio,nested,eventloop
Classifier: Development Status :: 5 - Production/Stable
Classifier: Intended Audience :: Developers
Classifier: License :: OSI Approved :: BSD License
Classifier: Programming Language :: Python :: 3.5
Classifier: Programming Language :: Python :: 3.6
Classifier: Programming Language :: Python :: 3.7
Classifier: Programming Language :: Python :: 3.8
Classifier: Programming Language :: Python :: 3.9
Classifier: Programming Language :: Python :: 3.10
Classifier: Programming Language :: Python :: 3.11
Classifier: Programming Language :: Python :: 3.12
Classifier: Programming Language :: Python :: 3 :: Only
Classifier: Framework :: AsyncIO
Requires-Python: >=3.5
License-File: LICENSE
